jupyter_micropython_extended_kernel/.ipynb_checkpoints/__init__-checkpoint.py
jupyter_micropython_extended_kernel/.ipynb_checkpoints/__main__-checkpoint.py
jupyter_micropython_extended_kernel/.ipynb_checkpoints/install-checkpoint.py
jupyter_micropython_extended_kernel/.ipynb_checkpoints/kernel-checkpoint.py
jupyter_micropython_extended_kernel/__init__.py
jupyter_micropython_extended_kernel/__main__.py
jupyter_micropython_extended_kernel/bleserial.py
jupyter_micropython_extended_kernel/connector.py
jupyter_micropython_extended_kernel/device.py
jupyter_micropython_extended_kernel/install.py
jupyter_micropython_extended_kernel/kernel.py
jupyter_micropython_extended_kernel/serialports.py
jupyter_micropython_extended_kernel-2025.1.1.dist-info/licenses/licenses/LICENSE
jupyter_micropython_extended_kernel-2025.1.1.dist-info/WHEEL
jupyter_micropython_extended_kernel-2025.1.1.dist-info/entry_points.txt
jupyter_micropython_extended_kernel-2025.1.1.dist-info/METADATA
jupyter_micropython_extended_kernel-2025.1.1.dist-info/RECORD
