Metadata-Version: 2.4
Name: jupyter-micropython-extended-kernel
Version: 2025.1.1
Summary: JupyterLab kernel to interact with a MicroPython ESP8266 or ESP32 over its serial REPL. For ESP32 it also allowes to connect over BLE. It provides IPython-cells from where MicroPython code and data can be accessed.
Keywords: MicroPython,ESP32,JupyterLab,kernel,BLE,IPython
Author: Alfred Fuchs
Author-email: Alfred Fuchs <a.fuchs@fosbos-rosenheim.de>
License-Expression: GPL-3.0-or-later
License-File: licenses/LICENSE
Classifier: Intended Audience :: Developers
Classifier: License :: OSI Approved :: BSD License
Classifier: Operating System :: OS Independent
Classifier: Programming Language :: Python
Classifier: Topic :: Software Development :: Libraries :: Python Modules
Requires-Dist: bleak>=0.22.3
Requires-Dist: pyserial>=3.4
Requires-Dist: unsync>=1.4.0
Requires-Dist: websocket-client>=0.44
Requires-Python: >=3.11
Project-URL: Homepage, https://github.com/a-fuchs/jupyter-micropython-extended-kernel
